sqlalchemy_gbasedbt/__init__.py
sqlalchemy_gbasedbt/dbtdb.py
sqlalchemy_gbasedbt/requirements.py
sqlalchemy_gbasedbt-0.2.4.2.dist-info/LICENSE
sqlalchemy_gbasedbt-0.2.4.2.dist-info/METADATA
sqlalchemy_gbasedbt-0.2.4.2.dist-info/WHEEL
sqlalchemy_gbasedbt-0.2.4.2.dist-info/entry_points.txt
sqlalchemy_gbasedbt-0.2.4.2.dist-info/top_level.txt
sqlalchemy_gbasedbt-0.2.4.2.dist-info/RECORD
