Metadata-Version: 2.1
Name: sqlalchemy_gbasedbt
Version: 0.2.4.2
Summary: SQLAlchemy GBase 8s backend
Home-page: https://gbasedbt.com
Author: Florian Apolloner, Dbt
Author-email: gbasedbt@gbasedbt.com
License: MIT License
Keywords: SQLAlchemy,GBasedbt
Platform: any
Classifier: Development Status :: 3 - Alpha
Classifier: Environment :: Console
Classifier: Intended Audience :: Developers
Classifier: Programming Language :: Python
Classifier: Programming Language :: Python :: 3
Classifier: Programming Language :: Python :: Implementation :: CPython
Classifier: Topic :: Database :: Front-Ends
License-File: LICENSE
Requires-Dist: DbtPy~=3.0.5.6
Requires-Dist: SQLAlchemy<2
